html_intersection/__init__.py
html_intersection/cli.py
html_intersection/core.py
html_intersection/utils.py
html_intersection-0.2.0.dist-info/licenses/LICENSE
html_intersection-0.2.0.dist-info/METADATA
html_intersection-0.2.0.dist-info/WHEEL
html_intersection-0.2.0.dist-info/entry_points.txt
html_intersection-0.2.0.dist-info/top_level.txt
html_intersection-0.2.0.dist-info/RECORD
