Metadata-Version: 2.4
Name: html-intersection
Version: 0.2.0
Summary: Fix canonical links, FLAGS, and RO<->EN cross-references across mirrored HTML directories.
Author: Andrei/Andreea Team
License: MIT
Project-URL: Homepage, https://pypi.org/project/html-intersection/
Project-URL: Repository, https://example.com/
Keywords: html,seo,canonical,flags,intersection,sync,ro,en
Classifier: Development Status :: 3 - Alpha
Classifier: Intended Audience :: Developers
Classifier: License :: OSI Approved :: MIT License
Classifier: Programming Language :: Python
Classifier: Programming Language :: Python :: 3
Classifier: Programming Language :: Python :: 3 :: Only
Classifier: Programming Language :: Python :: 3.8
Classifier: Programming Language :: Python :: 3.9
Classifier: Programming Language :: Python :: 3.10
Classifier: Programming Language :: Python :: 3.11
Classifier: Programming Language :: Python :: 3.12
Classifier: Topic :: Text Processing :: Markup :: HTML
Requires-Python: >=3.8
License-File: LICENSE
Dynamic: license-file
